geco_stat.py
geco_stat-0.2.1.dist-info/DESCRIPTION.rst
geco_stat-0.2.1.dist-info/METADATA
geco_stat-0.2.1.dist-info/RECORD
geco_stat-0.2.1.dist-info/WHEEL
geco_stat-0.2.1.dist-info/metadata.json
geco_stat-0.2.1.dist-info/top_level.txt
