Metadata-Version: 2.0
Name: geco-stat
Version: 0.2.1
Summary: Diagnostic tools for the advanced LIGO timing distribution system.
Home-page: https://github.com/stefco/geco_stat
Author: Stefan Countryman
Author-email: stefan.countryman@ligo.org
License: MIT
Keywords: lsc ligo geco columbia timing diagnostic gravitational waves frame
Platform: UNKNOWN
Classifier: Development Status :: 2 - Pre-Alpha
Classifier: Intended Audience :: Science/Research
Classifier: Topic :: Scientific/Engineering :: Physics
Classifier: License :: OSI Approved :: MIT License
Classifier: Programming Language :: Python :: 2
Classifier: Programming Language :: Python :: 2.6
Classifier: Programming Language :: Python :: 2.7
Classifier: Programming Language :: Python :: 3
Classifier: Programming Language :: Python :: 3.2
Classifier: Programming Language :: Python :: 3.3
Classifier: Programming Language :: Python :: 3.4
Classifier: Programming Language :: Python :: 3.5
Requires-Dist: h5py
Requires-Dist: matplotlib
Requires-Dist: numpy
Requires-Dist: tendo
Provides-Extra: dev
Requires-Dist: ipython; extra == 'dev'
Requires-Dist: pip (>=1.4); extra == 'dev'
Requires-Dist: setuptools (>=0.9); extra == 'dev'
Requires-Dist: twine; extra == 'dev'
Requires-Dist: wheel (>=0.21); extra == 'dev'
Provides-Extra: docs
Requires-Dist: recommonmark; extra == 'docs'
Requires-Dist: sphinx; extra == 'docs'
